LICENSE.txt
MANIFEST.in
README.rst
setup.cfg
setup.py
pyservertech/__init__.py
pyservertech/auth.py
pyservertech/core.py
pyservertech/objects.py
pyservertech.egg-info/PKG-INFO
pyservertech.egg-info/SOURCES.txt
pyservertech.egg-info/dependency_links.txt
pyservertech.egg-info/entry_points.txt
pyservertech.egg-info/requires.txt
pyservertech.egg-info/top_level.txt
test/test1.py
test/test_inputs.py
test/test_pyservertech_auth.py
test/test_pyservertech_core.py
test/test_pyservertech_objects.py