Metadata-Version: 1.1
Name: pyservertech
Version: 1.0.1
Summary: Python wrapper for Server Technologies SNMP interface
Home-page: https://github.com/netmanchris/pyservertech
Author: netmanchris
Author-email: chris_young@me.com
License: Apache2
Keywords: Server Technologies Smart PDU
Platform: UNKNOWN
Classifier: Development Status :: 3 - Alpha
Classifier: Intended Audience :: Developers
Classifier: Intended Audience :: System Administrators
Classifier: License :: OSI Approved :: Apache Software License
Classifier: Programming Language :: Python
Classifier: Natural Language :: English
Classifier: Operating System :: OS Independent
Classifier: Topic :: Software Development :: Libraries :: Python Modules
